ProgramizShujujiegouHeSuanfaJiaochengChuyiFix1/README.md
ProgramizShujujiegouHeSuanfaJiaochengChuyiFix1/__init__.py
ProgramizShujujiegouHeSuanfaJiaochengChuyiFix1/__main__.py
ProgramizShujujiegouHeSuanfaJiaochengChuyiFix1/file.epub
ProgramizShujujiegouHeSuanfaJiaochengChuyiFix1/index.html
ProgramizShujujiegouHeSuanfaJiaochengChuyiFix1/css/__init__.py
ProgramizShujujiegouHeSuanfaJiaochengChuyiFix1/css/annotations.css
ProgramizShujujiegouHeSuanfaJiaochengChuyiFix1/css/main.css
ProgramizShujujiegouHeSuanfaJiaochengChuyiFix1/css/normalize.css
ProgramizShujujiegouHeSuanfaJiaochengChuyiFix1/css/popup.css
ProgramizShujujiegouHeSuanfaJiaochengChuyiFix1/font/__init__.py
ProgramizShujujiegouHeSuanfaJiaochengChuyiFix1/font/fontello.eot
ProgramizShujujiegouHeSuanfaJiaochengChuyiFix1/font/fontello.svg
ProgramizShujujiegouHeSuanfaJiaochengChuyiFix1/font/fontello.ttf
ProgramizShujujiegouHeSuanfaJiaochengChuyiFix1/font/fontello.woff
ProgramizShujujiegouHeSuanfaJiaochengChuyiFix1/img/__init__.py
ProgramizShujujiegouHeSuanfaJiaochengChuyiFix1/img/annotator-glyph-sprite.png
ProgramizShujujiegouHeSuanfaJiaochengChuyiFix1/img/annotator-icon-sprite.png
ProgramizShujujiegouHeSuanfaJiaochengChuyiFix1/img/apple-touch-icon.png
ProgramizShujujiegouHeSuanfaJiaochengChuyiFix1/img/cancelfullscreen.png
ProgramizShujujiegouHeSuanfaJiaochengChuyiFix1/img/close.png
ProgramizShujujiegouHeSuanfaJiaochengChuyiFix1/img/fullscreen.png
ProgramizShujujiegouHeSuanfaJiaochengChuyiFix1/img/loader.gif
ProgramizShujujiegouHeSuanfaJiaochengChuyiFix1/img/menu-icon.png
ProgramizShujujiegouHeSuanfaJiaochengChuyiFix1/img/save.png
ProgramizShujujiegouHeSuanfaJiaochengChuyiFix1/img/saved.png
ProgramizShujujiegouHeSuanfaJiaochengChuyiFix1/img/settings-s.png
ProgramizShujujiegouHeSuanfaJiaochengChuyiFix1/img/settings.png
ProgramizShujujiegouHeSuanfaJiaochengChuyiFix1/img/star.png
ProgramizShujujiegouHeSuanfaJiaochengChuyiFix1/js/__init__.py
ProgramizShujujiegouHeSuanfaJiaochengChuyiFix1/js/epub.js
programiz_shujujiegou_he_suanfa_jiaocheng_chuyi_fix1-2025.3.24.0.dist-info/METADATA
programiz_shujujiegou_he_suanfa_jiaocheng_chuyi_fix1-2025.3.24.0.dist-info/WHEEL
programiz_shujujiegou_he_suanfa_jiaocheng_chuyi_fix1-2025.3.24.0.dist-info/entry_points.txt
programiz_shujujiegou_he_suanfa_jiaocheng_chuyi_fix1-2025.3.24.0.dist-info/top_level.txt
programiz_shujujiegou_he_suanfa_jiaocheng_chuyi_fix1-2025.3.24.0.dist-info/RECORD
